psgcompiler/LICENSE.txt
psgcompiler/README.md
psgcompiler/__init__.py
psgcompiler/__main__.py
psgcompiler/psgcompiler.py
psgcompiler/psgcompiler_icon.ico
psgcompiler/psgcompiler_icon.png
psgcompiler/screenshot.jpg
psgcompiler-5.0.0.dist-info/LICENSE.txt
psgcompiler-5.0.0.dist-info/METADATA
psgcompiler-5.0.0.dist-info/WHEEL
psgcompiler-5.0.0.dist-info/entry_points.txt
psgcompiler-5.0.0.dist-info/top_level.txt
psgcompiler-5.0.0.dist-info/RECORD
