Metadata-Version: 2.1
Name: psgcompiler
Version: 5.0.0
Summary: A simple, easy to use tool that is a front-end to PyInstaller created with PySimpleGUI to convert your Python programs to executables.
Home-page: https://github.com/PySimpleGUI/psgcompiler
Author: PySimpleSoft Inc.
License: Free To Use But Restricted
Keywords: GUI UI PySimpleGUI tkinter psgcompiler compile pyinstaller EXE distribute
Classifier: Development Status :: 5 - Production/Stable
Classifier: Intended Audience :: Developers
Classifier: License :: Free To Use But Restricted
Classifier: Operating System :: OS Independent
Classifier: Framework :: PySimpleGUI
Classifier: Framework :: PySimpleGUI :: 5
Classifier: Programming Language :: Python :: 3
Classifier: Programming Language :: Python :: 3.6
Classifier: Programming Language :: Python :: 3.7
Classifier: Programming Language :: Python :: 3.8
Classifier: Programming Language :: Python :: 3.9
Classifier: Programming Language :: Python :: 3.10
Classifier: Programming Language :: Python :: 3.11
Classifier: Programming Language :: Python :: 3.12
Classifier: Programming Language :: Python :: 3.13
Classifier: Topic :: Multimedia :: Graphics
Classifier: Topic :: Software Development :: User Interfaces
Requires-Python: >=3.6
License-File: LICENSE.txt
Requires-Dist: PySimpleGUI >=5
Requires-Dist: PyInstaller
